gradio_memotext/__init__.py
gradio_memotext/memotext.py
gradio_memotext/memotext.pyi
gradio_memotext/templates/component/Index-DgoXN_V5.js
gradio_memotext/templates/component/_basePickBy-a2P0SCtH.js
gradio_memotext/templates/component/_baseUniq-CTXzoHT4.js
gradio_memotext/templates/component/arc-BnvgHyiQ.js
gradio_memotext/templates/component/architectureDiagram-SUXI7LT5-D42OnI_G.js
gradio_memotext/templates/component/auto-render-BwaQGe8P.js
gradio_memotext/templates/component/blockDiagram-6J76NXCF-DygbHjk5.js
gradio_memotext/templates/component/c4Diagram-6F6E4RAY-CMD2osC1.js
gradio_memotext/templates/component/channel-B7ZUV6dy.js
gradio_memotext/templates/component/chunk-353BL4L5-8KEFOe1C.js
gradio_memotext/templates/component/chunk-67H74DCK-DDWxBxKT.js
gradio_memotext/templates/component/chunk-AACKK3MU-jTkhoSam.js
gradio_memotext/templates/component/chunk-BFAMUDN2-CIJ0zMxJ.js
gradio_memotext/templates/component/chunk-E2GYISFI-B6EFuLoR.js
gradio_memotext/templates/component/chunk-OW32GOEJ-DPtwu7h8.js
gradio_memotext/templates/component/chunk-SKB7J2MH-BZP2Z3JT.js
gradio_memotext/templates/component/chunk-SZ463SBG-H1Ra16tD.js
gradio_memotext/templates/component/classDiagram-M3E45YP4-W2fC2M8D.js
gradio_memotext/templates/component/classDiagram-v2-YAWTLIQI-W2fC2M8D.js
gradio_memotext/templates/component/clone-C-truQla.js
gradio_memotext/templates/component/cytoscape.esm-CphbmbIK.js
gradio_memotext/templates/component/dagre-JOIXM2OF-Bq0fVN9L.js
gradio_memotext/templates/component/defaultLocale-D7EN2tov.js
gradio_memotext/templates/component/diagram-5UYTHUR4-CHRLV4GJ.js
gradio_memotext/templates/component/diagram-VMROVX33-B9NP5vYC.js
gradio_memotext/templates/component/diagram-ZTM2IBQH-Dijc0YQf.js
gradio_memotext/templates/component/erDiagram-3M52JZNH-DB3rQhVm.js
gradio_memotext/templates/component/flowDiagram-KYDEHFYC-ByMRB4Nb.js
gradio_memotext/templates/component/ganttDiagram-EK5VF46D-HvjH7UZa.js
gradio_memotext-0.0.7.dist-info/METADATA
gradio_memotext-0.0.7.dist-info/WHEEL
gradio_memotext-0.0.7.dist-info/RECORD
